sloth_ci/validators/github.py
sloth_ci.validators.github-1.1.1.dist-info/DESCRIPTION.rst
sloth_ci.validators.github-1.1.1.dist-info/METADATA
sloth_ci.validators.github-1.1.1.dist-info/RECORD
sloth_ci.validators.github-1.1.1.dist-info/WHEEL
sloth_ci.validators.github-1.1.1.dist-info/metadata.json
sloth_ci.validators.github-1.1.1.dist-info/top_level.txt
