Metadata-Version: 2.0
Name: sloth-ci.validators.github
Version: 1.1.1
Summary: GitHub validator for Sloth CI
Home-page: https://bitbucket.org/moigagoo/sloth-ci-validators
Author: Konstantin Molchanov
Author-email: moigagoo@live.com
License: MIT
Platform: UNKNOWN
Classifier: Development Status :: 5 - Production/Stable
Classifier: Intended Audience :: Developers
Classifier: Natural Language :: English
Classifier: Programming Language :: Python
Classifier: Programming Language :: Python :: 3
Requires-Dist: sloth-ci (>=2.0.1)
